mmh2/__init__.py
mmh2/murmurhash2.py
mmh2/version.py
mmh2-0.1.0.dist-info/LICENSE
mmh2-0.1.0.dist-info/METADATA
mmh2-0.1.0.dist-info/WHEEL
mmh2-0.1.0.dist-info/RECORD
