Metadata-Version: 2.3
Name: mmh2
Version: 0.1.0
Summary: Python implementation of Austin Appleby's MurmurHash2 code.
License: MIT
Author: kurotom
Author-email: 55354389+kurotom@users.noreply.github.com
Requires-Python: >=3.9
Classifier: License :: OSI Approved :: MIT License
Classifier: Operating System :: OS Independent
Classifier: Programming Language :: Python :: 3.9
Classifier: Programming Language :: Python :: 3.10
Classifier: Programming Language :: Python :: 3.11
Classifier: Programming Language :: Python :: 3.12
